{
  "support": [
    {
      "id": "1778745399743",
      "price": 10.9,
      "note": "",
      "createdAt": "2026-05-14T07:56:39.743Z"
    },
    {
      "id": "1778745404634",
      "price": 11.3,
      "note": "",
      "createdAt": "2026-05-14T07:56:44.634Z"
    },
    {
      "id": "1778745651227",
      "price": 13.3,
      "note": "",
      "createdAt": "2026-05-14T08:00:51.227Z"
    },
    {
      "id": "1778745594029",
      "price": 14.3,
      "note": "",
      "createdAt": "2026-05-14T07:59:54.029Z"
    }
  ],
  "resistance": [
    {
      "id": "1778745656056",
      "price": 13.3,
      "note": "",
      "createdAt": "2026-05-14T08:00:56.056Z"
    },
    {
      "id": "1778745601465",
      "price": 14.3,
      "note": "",
      "createdAt": "2026-05-14T08:00:01.465Z"
    }
  ]
}